Metadata-Version: 2.1
Name: sztestlib2024
Version: 1.0.0
Summary: this is a niubi lib
Home-page: UNKNOWN
Author: Sz
Author-email: wangshu10@chinaunicom.cn
License: MIT
Platform: UNKNOWN
License-File: LICENSE.txt
